[
    {
        "key": "sb",
        "value": "hWwaY41XRBw3dPghMKhxlydH",
        "domain": "facebook.com",
        "path": "/",
        "hostOnly": false,
        "creation": "2022-09-12T01:14:12.517Z",
        "lastAccessed": "2022-09-12T01:14:12.517Z"
    },
    {
        "key": "locale",
        "value": "en_GB",
        "domain": "facebook.com",
        "path": "/",
        "hostOnly": false,
        "creation": "2022-09-12T01:14:12.517Z",
        "lastAccessed": "2022-09-12T01:14:12.517Z"
    },
    {
        "key": "wd",
        "value": "743x660",
        "domain": "facebook.com",
        "path": "/",
        "hostOnly": false,
        "creation": "2022-09-12T01:14:12.517Z",
        "lastAccessed": "2022-09-12T01:14:12.517Z"
    },
    {
        "key": "c_user",
        "value": "100085436205089",
        "domain": "facebook.com",
        "path": "/",
        "hostOnly": false,
        "creation": "2022-09-12T01:14:12.517Z",
        "lastAccessed": "2022-09-12T01:14:12.517Z"
    },
    {
        "key": "datr",
        "value": "g3gdY9C_Aj_2BFJU0Pj2Wkhg",
        "domain": "facebook.com",
        "path": "/",
        "hostOnly": false,
        "creation": "2022-09-12T01:14:12.517Z",
        "lastAccessed": "2022-09-12T01:14:12.517Z"
    },
    {
        "key": "xs",
        "value": "27%3AVZ0kUfm-8dBWLw%3A2%3A1662875777%3A-1%3A-1%3A%3AAcVxygZirNmeT99qtpWEdo0sb5zDZ9p6qgwzrxxVtg",
        "domain": "facebook.com",
        "path": "/",
        "hostOnly": false,
        "creation": "2022-09-12T01:14:12.517Z",
        "lastAccessed": "2022-09-12T01:14:12.517Z"
    },
    {
        "key": "fr",
        "value": "02OgqP5QY22BJfRbn.AWUpjY0PPsFPR-493FsUn41s9dA.BjHodG.c3.AAA.0.0.BjHodG.AWVQoRoTkHY",
        "domain": "facebook.com",
        "path": "/",
        "hostOnly": false,
        "creation": "2022-09-12T01:14:12.517Z",
        "lastAccessed": "2022-09-12T01:14:12.517Z"
    }
]